flask_pyMySQL2-2020.12-py3.8-nspkg.pth
flask_pymysql/mysql.py
flask_pyMySQL2-2020.12.dist-info/LICENSE
flask_pyMySQL2-2020.12.dist-info/METADATA
flask_pyMySQL2-2020.12.dist-info/WHEEL
flask_pyMySQL2-2020.12.dist-info/namespace_packages.txt
flask_pyMySQL2-2020.12.dist-info/top_level.txt
flask_pyMySQL2-2020.12.dist-info/RECORD
