Metadata-Version: 2.1
Name: flask-pyMySQL2
Version: 2020.12
Summary: Flask simple mysql client
Home-page: https://github.com/livermorium/flask-mysql.git
Author: livermorium
Author-email: UNKNOWN
License: MIT
Platform: any
Classifier: Environment :: Web Environment
Classifier: Intended Audience :: Developers
Classifier: License :: OSI Approved :: BSD License
Classifier: Operating System :: OS Independent
Classifier: Programming Language :: Python
Classifier: Topic :: Internet :: WWW/HTTP :: Dynamic Content
Classifier: Topic :: Software Development :: Libraries :: Python Modules
Requires-Dist: Flask
Requires-Dist: PyMySQL
